aimped/__init__.py
aimped/io_tasks.py
aimped/models.py
aimped/s3_file_manager.py
aimped/utils.py
aimped/version.py
aimped/model/__init__.py
aimped/model/load.py
aimped/nlp/__init__.py
aimped/nlp/assertion.py
aimped/nlp/chunker.py
aimped/nlp/deid.py
aimped/nlp/medical_coding.py
aimped/nlp/ner.py
aimped/nlp/ner_cls_report.py
aimped/nlp/pipeline.py
aimped/nlp/regex_parser.py
aimped/nlp/relation.py
aimped/nlp/relation_visualizer.py
aimped/nlp/tokenizer.py
aimped/nlp/tools.py
aimped/nlp/translation.py
aimped/nlp/translation_context.py
aimped/services/__init__.py
aimped/services/api.py
aimped/services/license.py
aimped/services/model_downloader.py
aimped/services/auth_service/__init__.py
aimped/services/auth_service/auth.py
aimped/sound/__init__.py
aimped/sound/utils.py
aimped/test/__init__.py
aimped/test/test_assertion.py
aimped/test/test_chunk_merger.py
aimped/test/test_deid_pipeline.py
aimped/test/test_ner_results.py
aimped/test/test_regex_parser.py
aimped/test/test_relation_pipeline.py
aimped/test/test_tokenizer.py
aimped/test/test_translation_pipeline.py
aimped-0.2.54.dist-info/LICENSE
aimped-0.2.54.dist-info/METADATA
aimped-0.2.54.dist-info/WHEEL
aimped-0.2.54.dist-info/top_level.txt
aimped-0.2.54.dist-info/RECORD
