Metadata-Version: 2.1
Name: aimped
Version: 0.2.54
Summary: Aimped is a unique library that provides classes and functions for only exclusively business-tailored AI-based NLP models.
Home-page: https://aimped.ai/
Author: F. Faraday
Author-email: forest@aimped.ai
Maintainer: aimped
Maintainer-email: contact@aimped.ai
Classifier: Programming Language :: Python :: 3
Classifier: License :: OSI Approved :: MIT License
Classifier: Operating System :: OS Independent
Requires-Python: >=3.8
License-File: LICENSE
Requires-Dist: nltk
Requires-Dist: pandas
Requires-Dist: scikit-learn
Requires-Dist: pydantic
Requires-Dist: neo4j
Requires-Dist: cryptography
Requires-Dist: boto3
Requires-Dist: jwt
